hat/duktape/duktape.so
hat/duktape/interpreter.py
hat/duktape/lib.py
hat/duktape/__init__.py
hat_duktape-0.5.8.dist-info/LICENSE
hat_duktape-0.5.8.dist-info/METADATA
hat_duktape-0.5.8.dist-info/WHEEL
hat_duktape-0.5.8.dist-info/RECORD
