Metadata-Version: 2.1
Name: hat-duktape
Version: 0.5.8
Summary: Hat Python Duktape JS wrapper
License: Apache-2.0
Classifier: Programming Language :: Python :: 3
Classifier: License :: OSI Approved :: Apache Software License
Provides-Extra: dev
Requires-Dist: hat-doit ~=0.15.13; extra == 'dev'
Requires-Python: >=3.10
Project-URL: Homepage, http://hat-open.com
Project-URL: Repository, https://github.com/hat-open/hat-duktape.git
Project-URL: Documentation, http://hat-duktape.hat-open.com
